gvgames/__init__.py
gvgames/g_games.py
gvgames-1.0.dist-info/METADATA
gvgames-1.0.dist-info/WHEEL
gvgames-1.0.dist-info/top_level.txt
gvgames-1.0.dist-info/RECORD
