Metadata-Version: 2.1
Name: gvgames
Version: 1.0
Summary: These are 2 games 1st is Guess the Number and 2nd is Snake and Ladder Game. these Both are Console games.
Author: GHANSHYAM VAJA
Author-email: ghanshyamvaja11@gmail.com
Classifier: Programming Language :: Python :: 3
Classifier: Operating System :: OS Independent
